musicbrainzez/__init__.py
musicbrainzez/_version.py
musicbrainzez/caa.py
musicbrainzez/compat.py
musicbrainzez/mbsubmission.py
musicbrainzez/musicbrainz.py
musicbrainzez/util.py
musicbrainzngs/__init__.py
musicbrainzngs/caa.py
musicbrainzngs/compat.py
musicbrainzngs/musicbrainz.py
musicbrainzez-1.1.dist-info/COPYING
musicbrainzez-1.1.dist-info/METADATA
musicbrainzez-1.1.dist-info/WHEEL
musicbrainzez-1.1.dist-info/top_level.txt
musicbrainzez-1.1.dist-info/RECORD
