Metadata-Version: 2.1
Name: musicbrainzez
Version: 1.1
Summary: Python bindings for the MusicBrainz and the Cover Art Archive webservices
Author-email: Louis Rannou <louson@gresille.org>
Project-URL: Homepage, https://gitlab.com/Louson/python-musicbrainzez
Classifier: Programming Language :: Python :: 3
Classifier: License :: OSI Approved :: BSD License
Classifier: License :: OSI Approved :: ISC License (ISCL)
Classifier: Operating System :: OS Independent
Classifier: Intended Audience :: Developers
Requires-Python: >=3.10
License-File: COPYING
